song/__init__.py
song/cli.py
song/commands/FactoryProducer.py
song/commands/FileDownload.py
song/commands/__init__.py
song/commands/base.py
song/commands/download.py
song/commands/parse.py
song/commands/search.py
song/commands/MusicWebsiteParser/MrJattParser.py
song/commands/MusicWebsiteParser/MusicWebsiteFactory.py
song/commands/MusicWebsiteParser/MusicWebsiteParser.py
song/commands/MusicWebsiteParser/YoutubeParser.py
song/commands/MusicWebsiteParser/__init__.py
song/commands/SearchEngineParser/GoogleParser.py
song/commands/SearchEngineParser/SearchEngineFactory.py
song/commands/SearchEngineParser/SearchEngineParser.py
song/commands/SearchEngineParser/__init__.py
song-2.9.2.dist-info/DESCRIPTION.rst
song-2.9.2.dist-info/METADATA
song-2.9.2.dist-info/RECORD
song-2.9.2.dist-info/WHEEL
song-2.9.2.dist-info/entry_points.txt
song-2.9.2.dist-info/metadata.json
song-2.9.2.dist-info/top_level.txt
