Metadata-Version: 2.0
Name: song
Version: 2.9.2
Summary: A script to download hindi and punjabi songs from internet
Home-page: https://github.com/ankitmathur3193/song-cli
Author: ankit mathur
Author-email: ankitmathur.dtu@gmail.com
License: MIT
Keywords: song,download,script,youtube-dl,tqdm,requests,beautiful soup
Platform: UNKNOWN
Classifier: Intended Audience :: Developers
Classifier: Topic :: Utilities
Classifier: License :: Public Domain
Classifier: Natural Language :: English
Classifier: Operating System :: OS Independent
Classifier: Programming Language :: Python :: 2
Classifier: Programming Language :: Python :: 2.6
Classifier: Programming Language :: Python :: 2.7
Requires-Dist: BeautifulSoup (==3.2.1)
Requires-Dist: docopt (==0.6.2)
Requires-Dist: requests (==2.16.4)
Requires-Dist: tqdm (==4.11.2)
Requires-Dist: youtube-dl (==2017.05.26)
